softcomputing/City & Fitness.py
softcomputing/Delta.py
softcomputing/Fuzzy Ratios.py
softcomputing/Genetic Algo.py
softcomputing/Heb.py
softcomputing/Hopfield.py
softcomputing/HopfieldAsssociative.py
softcomputing/Kohonen.py
softcomputing/Linear Separability.py
softcomputing/McCulloch-Pitts Net Input2A.py
softcomputing/RadialBasis.py
softcomputing/Tipping.py
softcomputing/XOR Function using MCP Network.py
softcomputing/__init__.py
softcomputing/backpropogation.py
softcomputing/binary and bipolar sigmoidal.py
softcomputing/error Backpropagation.py
softcomputing/operators.py
softcomputing/simple linear neural.py
softcomputing_jyoti-0.2.0.dist-info/licenses/LICENSE
softcomputing_jyoti-0.2.0.dist-info/METADATA
softcomputing_jyoti-0.2.0.dist-info/WHEEL
softcomputing_jyoti-0.2.0.dist-info/top_level.txt
softcomputing_jyoti-0.2.0.dist-info/RECORD
