Metadata-Version: 2.4
Name: softcomputing-jyoti
Version: 0.2.0
Summary: A collection of neural network implementations and soft computing algorithms
Home-page: https://github.com/jyotirahate/softcomputing
Author: Jyoti Rahate
Author-email: your.email@example.com
Classifier: Programming Language :: Python :: 3
Classifier: License :: OSI Approved :: MIT License
Classifier: Operating System :: OS Independent
Requires-Python: >=3.7
License-File: LICENSE
Requires-Dist: minisom
Requires-Dist: neurodynex
Requires-Dist: fuzzywuzzy
Requires-Dist: python-Levenshtein
Requires-Dist: scikit-fuzzy
Requires-Dist: networkx
Requires-Dist: numpy
Requires-Dist: scipy
Requires-Dist: matplotlib
Dynamic: author
Dynamic: author-email
Dynamic: classifier
Dynamic: description
Dynamic: description-content-type
Dynamic: home-page
Dynamic: license-file
Dynamic: requires-dist
Dynamic: requires-python
Dynamic: summary
